docs/build/html/_sources/changelog.rst.txt
docs/build/html/_sources/contributing.rst.txt
docs/build/html/_sources/examples.rst.txt
docs/build/html/_sources/index.rst.txt
docs/build/html/_sources/installation.rst.txt
docs/build/html/_sources/quickstart.rst.txt
docs/build/html/_sources/api/modules.rst.txt
docs/build/html/_sources/api/_autosummary/lcvtoolbox.cli.main.rst.txt
docs/build/html/_sources/api/_autosummary/lcvtoolbox.cli.rst.txt
docs/build/html/_sources/api/_autosummary/lcvtoolbox.core.rst.txt
docs/build/html/_sources/api/_autosummary/lcvtoolbox.core.schemas.Annotation.rst.txt
docs/build/html/_sources/api/_autosummary/lcvtoolbox.core.schemas.CameraDistortionSchema.rst.txt
docs/build/html/_sources/api/_autosummary/lcvtoolbox.core.schemas.CameraMatrixSchema.rst.txt
docs/build/html/_sources/api/_autosummary/lcvtoolbox.core.schemas.CocoRleDict.rst.txt
docs/build/html/_sources/api/_autosummary/lcvtoolbox.core.schemas.CvatApiAttribute.rst.txt
docs/build/html/_sources/api/_autosummary/lcvtoolbox.core.schemas.CvatApiAttributeDefinition.rst.txt
docs/build/html/_sources/api/_autosummary/lcvtoolbox.core.schemas.CvatApiAttributeDefinitionDict.rst.txt
docs/build/html/_sources/api/_autosummary/lcvtoolbox.core.schemas.CvatApiAttributeDict.rst.txt
docs/build/html/_sources/api/_autosummary/lcvtoolbox.core.schemas.CvatApiJobAnnotations.rst.txt
docs/build/html/_sources/api/_autosummary/lcvtoolbox.core.schemas.CvatApiJobAnnotationsDict.rst.txt
docs/build/html/_sources/api/_autosummary/lcvtoolbox.core.schemas.CvatApiJobDetails.rst.txt
docs/build/html/_sources/api/_autosummary/lcvtoolbox.core.schemas.CvatApiJobDetailsDict.rst.txt
docs/build/html/_sources/api/_autosummary/lcvtoolbox.core.schemas.CvatApiJobMediasMetainformation.rst.txt
docs/build/html/_sources/api/_autosummary/lcvtoolbox.core.schemas.CvatApiJobMediasMetainformationDict.rst.txt
docs/build/html/_sources/api/_autosummary/lcvtoolbox.core.schemas.CvatApiLabelDefinition.rst.txt
lcvtoolbox-1.0.7.dist-info/METADATA
lcvtoolbox-1.0.7.dist-info/WHEEL
lcvtoolbox-1.0.7.dist-info/entry_points.txt
lcvtoolbox-1.0.7.dist-info/top_level.txt
lcvtoolbox-1.0.7.dist-info/RECORD
